{
  "type": "Feature",
  "properties": {
    "gn:country":"KW",
    "gn:fcode":"PPLL",
    "gn:population":1878,
    "iso:country":"KW",
    "name:ara_x_preferred":[
        "\u0627\u064e\u0644\u0652\u0641\u064f\u0646\u064e\u064a\u0652\u0637\u0650\u064a\u0633"
    ],
    "name:ara_x_variant":[
        "\u0627\u0644\u0641\u0646\u064a\u0637\u064a\u0633"
    ],
    "name:und_x_variant":[
        "Al Fanaitis"
    ],
    "qs:name":"Al Funay\u0163\u012bs",
    "qs:photos_9r":0,
    "qs:photos_sr":0,
    "qs:pop_sr":"3",
    "wof:name":"Al Funay\u0163\u012bs",
    "wof:placetype":"locality",
    "wof:population":1878
},
  "geometry": {"coordinates":[48.10167,29.22528],"type":"Point"}
}