{
  "type": "Feature",
  "properties": {
    "iso:country":"KW",
    "qs:gn_pop":0,
    "qs:name":"Mutlaa",
    "qs:name_adm0":"\u0627\u0644\u0643\u0648\u064a\u062a",
    "qs:name_adm1":"\u0627\u0644\u062c\u0647\u0631\u0627\u0621",
    "qs:photos":109,
    "qs:photos_1k":22,
    "qs:photos_9k":1,
    "qs:photos_9r":3,
    "qs:photos_all":109,
    "qs:photos_sr":3,
    "qs:placetype":"Town",
    "qs:pop_sr":"0",
    "qs:woe_adm0":23424870,
    "wof:name":"Mutlaa",
    "wof:placetype":"locality"
},
  "geometry": {"coordinates":[47.69989,29.411881],"type":"Point"}
}