{
  "type": "Feature",
  "properties": {
    "gn:admin1_code":"4.0",
    "gn:asciiname":"Az Zawr",
    "gn:cc2":"KW",
    "gn:country_code":"KW",
    "gn:dem":5,
    "gn:feature_class":"P",
    "gn:feature_code":"PPL",
    "gn:name":"Az Zawr",
    "gn:population":0,
    "gn:timezone":"Asia/Kuwait",
    "iso:country":"KW",
    "name:ara_x_preferred":[
        "\u0627\u064e\u0644\u0632\u064e\u0651\u0648\u0652\u0631"
    ],
    "name:und_x_variant":[
        "M\u012bn\u0101\u2019 az Zawr",
        "M\u012bn\u0101\u2019 Sa\u2018\u016bd",
        "Min\u0101\u2019 az-Zor",
        "Az Zawr"
    ],
    "wof:lang_x_official":[
        "ara"
    ],
    "wof:lang_x_spoken":[
        "ara"
    ],
    "wof:name":"Az Zawr",
    "wof:placetype":"locality"
},
  "geometry": {"coordinates":[48.37278,28.7375],"type":"Point"}
}