{
  "type": "Feature",
  "properties": {
    "iso:country":"KW",
    "name:ara_x_preferred":[
        "\u0627\u0644\u0632\u0628\u064a\u0631"
    ],
    "name:arz_x_preferred":[
        "\u0627\u0644\u0632\u0628\u064a\u0631"
    ],
    "name:deu_x_preferred":[
        "Zubair"
    ],
    "name:eng_x_preferred":[
        "Al Zubair"
    ],
    "name:est_x_preferred":[
        "Az-Zubayr"
    ],
    "name:fas_x_preferred":[
        "\u0632\u0628\u06cc\u0631\u060c \u0639\u0631\u0627\u0642"
    ],
    "name:jpn_x_preferred":[
        "\u30ba\u30d0\u30a4\u30eb"
    ],
    "name:kat_x_preferred":[
        "\u10d0\u10da-\u10d6\u10e3\u10d1\u10d0\u10d8\u10e0\u10d8"
    ],
    "name:kaz_x_preferred":[
        "\u042d\u0437-\u0417\u0443\u0431\u0430\u0439\u0440"
    ],
    "name:mzn_x_preferred":[
        "\u0632\u0628\u06cc\u0631\u060c \u0639\u0631\u0627\u0642"
    ],
    "name:pnb_x_preferred":[
        "\u0627\u0644\u0632\u0628\u064a\u0631"
    ],
    "name:pol_x_preferred":[
        "Az-Zubajr"
    ],
    "name:rus_x_preferred":[
        "\u042d\u0437-\u0417\u0443\u0431\u0430\u0439\u0440"
    ],
    "name:spa_x_preferred":[
        "Az Zubayr"
    ],
    "name:tur_x_preferred":[
        "Ez-Z\u00fcbeyr"
    ],
    "name:urd_x_preferred":[
        "\u0632\u0628\u06cc\u0631"
    ],
    "name:zho_x_preferred":[
        "\u7956\u62dc\u723e"
    ],
    "qs:gn_pop":0,
    "qs:name":"Al Zubair",
    "qs:name_adm0":"Iraq",
    "qs:name_adm1":"\u0627\u0644\u0628\u0635\u0631\u0629",
    "qs:photos":132,
    "qs:photos_1k":27,
    "qs:photos_9k":1,
    "qs:photos_9r":3,
    "qs:photos_all":132,
    "qs:photos_sr":3,
    "qs:placetype":"County",
    "qs:pop_sr":"0",
    "qs:woe_adm0":23424855,
    "wd:wordcount":311,
    "wof:name":"Al Zubair",
    "wof:placetype":"county"
},
  "geometry": {"coordinates":[47.7398695,30.013219],"type":"Point"}
}