{
  "type": "Feature",
  "properties": {
    "iso:country":"KW",
    "name:ara_x_preferred":[
        "\u0627\u0644\u0641\u0631\u0648\u0627\u0646\u064a\u0629"
    ],
    "name:eng_x_preferred":[
        "Farwaniya"
    ],
    "qs:gn_pop":0,
    "qs:name":"\u0627\u0644\u0641\u0631\u0648\u0627\u0646\u064a\u0629",
    "qs:name_adm0":"\u0627\u0644\u0643\u0648\u064a\u062a",
    "qs:name_adm1":"\u0627\u0644\u0641\u0631\u0648\u0627\u0646\u064a\u0629",
    "qs:photos":63,
    "qs:photos_1k":13,
    "qs:photos_9k":13,
    "qs:photos_9r":11,
    "qs:photos_all":2966,
    "qs:photos_sr":2,
    "qs:placetype":"County",
    "qs:pop_sr":"0",
    "qs:woe_adm0":23424870,
    "wof:name":"Farwaniya",
    "wof:placetype":"county"
},
  "geometry": {"coordinates":[47.91687,29.250459],"type":"Point"}
}