{
  "type": "Feature",
  "properties": {
    "iso:country":"KW",
    "name:eng_x_preferred":[
        "Yarmouk-block 3"
    ],
    "qs:gn_local":0,
    "qs:local_max":193,
    "qs:local_sum":269,
    "qs:localhoods":3,
    "qs:name":"Yarmouk-block 3",
    "qs:name_adm0":"\u0627\u0644\u0643\u0648\u064a\u062a",
    "qs:name_adm1":"\u0627\u0644\u0641\u0631\u0648\u0627\u0646\u064a\u0629",
    "qs:name_adm2":"\u0627\u0644\u0641\u0631\u0648\u0627\u0646\u064a\u0629",
    "qs:name_local":"Yarmouk",
    "qs:photo_max":9,
    "qs:photo_sum":12,
    "qs:placetype":"Suburb",
    "qs:quad_count":3,
    "qs:woe_adm0":23424870,
    "qs:woe_adm1":20070168,
    "qs:woe_adm2":55943082,
    "qs:woe_lau":0,
    "qs:woe_local":1940567,
    "qs:woe_ver":"7.10.0",
    "wof:lang_x_official":[
        "ara"
    ],
    "wof:lang_x_spoken":[
        "ara"
    ],
    "wof:name":"Yarmouk-block 3",
    "wof:placetype":"microhood"
},
  "geometry": {"coordinates":[47.968738,29.306943],"type":"Point"}
}