{
  "type": "Feature",
  "properties": {
    "iso:country":"KW",
    "name:ara_x_preferred":[
        "\u0627\u0644\u0635\u0644\u064a\u0628\u064a\u062e\u0627\u062a"
    ],
    "name:ara_x_variant":[
        "\u0627\u064e\u0644\u0635\u064f\u0651\u0644\u064e\u064a\u0652\u0628\u0650\u064a\u062e\u064e\u0627\u062a"
    ],
    "name:deu_x_preferred":[
        "Sulaibikhat"
    ],
    "name:eng_x_preferred":[
        "As Sulaybikhat"
    ],
    "name:eng_x_variant":[
        "A\u015f \u015eulayb\u012bkh\u0101t",
        "Sulaibikhat"
    ],
    "name:fra_x_preferred":[
        "Sulaibikhat"
    ],
    "name:nld_x_preferred":[
        "Sulaibikhat"
    ],
    "name:nno_x_preferred":[
        "Sulaibikhat"
    ],
    "name:rus_x_preferred":[
        "\u0421\u0443\u043b\u0430\u0439\u0431\u0438\u0445\u0430\u0442"
    ],
    "name:spa_x_preferred":[
        "Sulaibikhat"
    ],
    "qs:gn_adm0_cc":"KW",
    "qs:gn_fcode":"PPLX",
    "qs:gn_local":285787,
    "qs:gn_nam_loc":"\u0645\u062f\u064a\u0646\u0629 \u0627\u0644\u0643\u0648\u064a\u062a, \u0645\u062f\u064a\u0646\u0629 \u0627\u0644\u0643\u0648\u064a\u062a, \u0645\u062f\u064a\u0646\u0629 \u0627\u0644\u0643\u0648\u064a\u062a, KW",
    "qs:gn_namadm1":"00",
    "qs:gn_name":"A\u015f \u015eulayb\u012bkh\u0101t",
    "qs:local_max":1268,
    "qs:local_sum":5995,
    "qs:localhoods":31,
    "qs:name":"As Sulaybikhat",
    "qs:name_adm0":"\u0627\u0644\u0643\u0648\u064a\u062a",
    "qs:name_adm1":"\u0645\u062f\u064a\u0646\u0629 \u0627\u0644\u0643\u0648\u064a\u062a",
    "qs:name_adm2":"\u0645\u062f\u064a\u0646\u0629 \u0627\u0644\u0643\u0648\u064a\u062a",
    "qs:name_local":"\u0645\u062f\u064a\u0646\u0629 \u0627\u0644\u0643\u0648\u064a\u062a",
    "qs:photo_max":2,
    "qs:photo_sum":7,
    "qs:placetype":"Suburb",
    "qs:quad_count":5,
    "qs:woe_adm0":23424870,
    "qs:woe_adm1":20070169,
    "qs:woe_adm2":55943085,
    "qs:woe_lau":0,
    "qs:woe_local":1940631,
    "qs:woe_ver":"7.10.0",
    "wd:wordcount":120,
    "wof:lang":[
        "eng"
    ],
    "wof:name":"As Sulaybikhat",
    "wof:placetype":"neighbourhood"
},
  "geometry": {"coordinates":[47.832511,29.315483],"type":"Point"}
}