{
  "type": "Feature",
  "properties": {
    "iso:country":"KW",
    "name:ara_x_preferred":[
        "\u0627\u064e\u0644\u0634\u064f\u0651\u0648\u064e\u064a\u0652\u062e"
    ],
    "name:unk_x_variant":[
        "Bander Shweikh"
    ],
    "qs:gn_country":"KW",
    "qs:gn_fcode":"PPLX",
    "qs:gn_pop":0,
    "qs:name":"Ash Shuwaykh",
    "qs:name_adm0":"\u0627\u0644\u0643\u0648\u064a\u062a",
    "qs:name_adm1":"\u0645\u062f\u064a\u0646\u0629 \u0627\u0644\u0643\u0648\u064a\u062a",
    "qs:photos":15,
    "qs:photos_1k":3,
    "qs:photos_9k":1,
    "qs:photos_9r":1,
    "qs:photos_all":15,
    "qs:photos_sr":1,
    "qs:placetype":"Suburb",
    "qs:pop_sr":"0",
    "qs:woe_adm0":23424870,
    "wof:name":"Ash Shuwaykh",
    "wof:placetype":"neighbourhood"
},
  "geometry": {"coordinates":[47.94611,29.34361],"type":"Point"}
}