{
  "type": "Feature",
  "properties": {
    "iso:country":"KW",
    "name:eng_x_preferred":[
        "Mishref-block 2"
    ],
    "qs:gn_local":0,
    "qs:local_max":453,
    "qs:local_sum":498,
    "qs:localhoods":3,
    "qs:name":"Mishref-block 2",
    "qs:name_adm0":"\u0627\u0644\u0643\u0648\u064a\u062a",
    "qs:name_adm1":"\u062d\u0648\u0644\u0649",
    "qs:name_adm2":"\u062d\u0648\u0644\u0649",
    "qs:name_local":"Mishrif",
    "qs:photo_max":9,
    "qs:photo_sum":29,
    "qs:placetype":"Suburb",
    "qs:quad_count":6,
    "qs:woe_adm0":23424870,
    "qs:woe_adm1":20070167,
    "qs:woe_adm2":55943084,
    "qs:woe_lau":0,
    "qs:woe_local":22724742,
    "qs:woe_ver":"7.10.0",
    "wof:lang":[
        "eng"
    ],
    "wof:name":"Mishref-block 2",
    "wof:placetype":"neighbourhood"
},
  "geometry": {"coordinates":[48.066869,29.28354],"type":"Point"}
}