{
  "type": "Feature",
  "properties": {
    "gn:admin1_code":"0.0",
    "gn:asciiname":"Ju`aydan",
    "gn:country_code":"KW",
    "gn:dem":69,
    "gn:feature_class":"P",
    "gn:feature_code":"PPL",
    "gn:name":"Ju\u2018ayd\u0101n",
    "gn:population":0,
    "gn:timezone":"Asia/Kuwait",
    "iso:country":"KW",
    "name:ara_x_preferred":[
        "\u062c\u064f\u0639\u064e\u064a\u0652\u062f\u064e\u0627\u0646"
    ],
    "name:und_x_variant":[
        "Juaidan",
        "Ju\u2018ayd\u0101n"
    ],
    "wof:lang_x_official":[
        "ara"
    ],
    "wof:lang_x_spoken":[
        "ara"
    ],
    "wof:name":"Ju`aydan",
    "wof:placetype":"locality"
},
  "geometry": {"coordinates":[47.96722,28.96667],"type":"Point"}
}