{
  "type": "Feature",
  "properties": {
    "iso:country":"KW",
    "qs:gn_pop":0,
    "qs:name":"Abu Hulaifa",
    "qs:name_adm0":"\u0627\u0644\u0643\u0648\u064a\u062a",
    "qs:name_adm1":"\u0627\u0644\u0623\u062d\u0645\u062f\u0649",
    "qs:photos":18,
    "qs:photos_1k":4,
    "qs:photos_9k":1,
    "qs:photos_9r":4,
    "qs:photos_all":170,
    "qs:photos_sr":1,
    "qs:placetype":"Town",
    "qs:pop_sr":"0",
    "qs:woe_adm0":23424870,
    "wof:name":"Abu Hulaifa",
    "wof:placetype":"locality"
},
  "geometry": {"coordinates":[48.1328465,29.1247975],"type":"Point"}
}