{
  "type": "Feature",
  "properties": {
    "iso:country":"KW",
    "qs:gn_pop":0,
    "qs:name":"Abdulla Al Mubarak Al Sabah",
    "qs:name_adm0":"\u0627\u0644\u0643\u0648\u064a\u062a",
    "qs:name_adm1":"\u0627\u0644\u0641\u0631\u0648\u0627\u0646\u064a\u0629",
    "qs:photos":25,
    "qs:photos_1k":5,
    "qs:photos_9k":1,
    "qs:photos_9r":4,
    "qs:photos_all":209,
    "qs:photos_sr":1,
    "qs:placetype":"Town",
    "qs:pop_sr":"0",
    "qs:woe_adm0":23424870,
    "wof:name":"Abdulla Al Mubarak Al Sabah",
    "wof:placetype":"locality"
},
  "geometry": {"coordinates":[47.919445,29.270377],"type":"Point"}
}