{
  "type": "Feature",
  "properties": {
    "gn:admin1_code":"0.0",
    "gn:asciiname":"Al `Uqaylah",
    "gn:country_code":"KW",
    "gn:dem":28,
    "gn:feature_class":"P",
    "gn:feature_code":"PPLL",
    "gn:name":"Al \u2018Uqaylah",
    "gn:population":0,
    "gn:timezone":"Asia/Kuwait",
    "iso:country":"KW",
    "name:ara_x_preferred":[
        "\u0627\u064e\u0644\u0652\u0639\u064f\u0642\u064e\u064a\u0652\u0644\u064e\u0629"
    ],
    "name:und_x_variant":[
        "\u2018Uqaila",
        "Al \u2018Uqlah",
        "\u2018Uqlah",
        "Ugla",
        "\u2018Uqallah",
        "Al \u2018Uqaylah"
    ],
    "wof:name":"Al `Uqaylah",
    "wof:placetype":"locality"
},
  "geometry": {"coordinates":[48.09472,29.17778],"type":"Point"}
}