{
  "type": "Feature",
  "properties": {
    "iso:country":"KW",
    "name:eng_x_preferred":[
        "Hateen-block 3"
    ],
    "name:unk_x_variant":[
        "Hateen-block 3"
    ],
    "qs:gn_local":0,
    "qs:local_max":26,
    "qs:local_sum":26,
    "qs:localhoods":1,
    "qs:name":"Hateen-block 3",
    "qs:name_adm0":"\u0627\u0644\u0643\u0648\u064a\u062a",
    "qs:name_adm1":"\u062d\u0648\u0644\u0649",
    "qs:name_adm2":"\u062d\u0648\u0644\u0649",
    "qs:name_local":"\u062d\u0637\u064a\u0646",
    "qs:photo_max":14,
    "qs:photo_sum":26,
    "qs:placetype":"Suburb",
    "qs:quad_count":6,
    "qs:woe_adm0":23424870,
    "qs:woe_adm1":20070167,
    "qs:woe_adm2":55943084,
    "qs:woe_lau":0,
    "qs:woe_local":10644940,
    "qs:woe_ver":"7.10.0",
    "wof:lang":[
        "eng"
    ],
    "wof:name":"Hateen-block 3",
    "wof:placetype":"neighbourhood"
},
  "geometry": {"coordinates":[48.024409,29.272578],"type":"Point"}
}