{
  "type": "Feature",
  "properties": {
    "iso:country":"KW",
    "name:ara_x_preferred":[
        "\u0627\u0644\u0634\u0647\u062f\u0627\u0621"
    ],
    "name:eng_x_preferred":[
        "Al Shuhada"
    ],
    "qs:gn_pop":0,
    "qs:name":"\u0627\u0644\u0634\u0647\u062f\u0627\u0621",
    "qs:name_adm0":"\u0627\u0644\u0643\u0648\u064a\u062a",
    "qs:name_adm1":"\u062d\u0648\u0644\u0649",
    "qs:photos":41,
    "qs:photos_1k":8,
    "qs:photos_9k":1,
    "qs:photos_9r":2,
    "qs:photos_all":41,
    "qs:photos_sr":2,
    "qs:placetype":"Town",
    "qs:pop_sr":"0",
    "qs:woe_adm0":23424870,
    "wof:name":"Al Shuhada",
    "wof:placetype":"locality"
},
  "geometry": {"coordinates":[48.025301,29.255211],"type":"Point"}
}