{
  "type": "Feature",
  "properties": {
    "gn:admin1_code":"0.0",
    "gn:asciiname":"Al Qulay`ah",
    "gn:country_code":"KW",
    "gn:dem":4,
    "gn:feature_class":"P",
    "gn:feature_code":"PPLL",
    "gn:name":"Al Qulay\u2018ah",
    "gn:population":0,
    "gn:timezone":"Asia/Kuwait",
    "iso:country":"KW",
    "name:ara_x_preferred":[
        "\u0627\u064e\u0644\u0652\u0642\u064f\u0644\u064e\u064a\u0652\u0639\u064e\u0629"
    ],
    "name:und_x_variant":[
        "Al Qulay\u2018ah"
    ],
    "wof:lang_x_official":[
        "ara"
    ],
    "wof:lang_x_spoken":[
        "ara"
    ],
    "wof:name":"Al Qulay`ah",
    "wof:placetype":"locality"
},
  "geometry": {"coordinates":[48.27472,28.86583],"type":"Point"}
}