{
  "type": "Feature",
  "properties": {
    "iso:country":"KW",
    "qs:gn_pop":0,
    "qs:name":"\u0627\u0644\u0648\u0641\u0631\u0629",
    "qs:name_adm0":"\u0627\u0644\u0643\u0648\u064a\u062a",
    "qs:name_adm1":"\u0627\u0644\u0623\u062d\u0645\u062f\u0649",
    "qs:photos":34,
    "qs:photos_1k":7,
    "qs:photos_9k":1,
    "qs:photos_9r":4,
    "qs:photos_all":210,
    "qs:photos_sr":2,
    "qs:placetype":"County",
    "qs:pop_sr":"0",
    "qs:woe_adm0":23424870,
    "wof:name":"\u0627\u0644\u0648\u0641\u0631\u0629",
    "wof:placetype":"county"
},
  "geometry": {"coordinates":[47.988281,28.639994],"type":"Point"}
}