{
  "type": "Feature",
  "properties": {
    "iso:country":"KW",
    "name:eng_x_preferred":[
        "Salhiya-block 5"
    ],
    "qs:gn_adm0_cc":"KW",
    "qs:gn_local":285787,
    "qs:gn_nam_loc":"\u0645\u062f\u064a\u0646\u0629 \u0627\u0644\u0643\u0648\u064a\u062a, \u0645\u062f\u064a\u0646\u0629 \u0627\u0644\u0643\u0648\u064a\u062a, \u0645\u062f\u064a\u0646\u0629 \u0627\u0644\u0643\u0648\u064a\u062a, KW",
    "qs:gn_namadm1":"02",
    "qs:local_max":1268,
    "qs:local_sum":5995,
    "qs:localhoods":31,
    "qs:name":"Salhiya-block 5",
    "qs:name_adm0":"\u0627\u0644\u0643\u0648\u064a\u062a",
    "qs:name_adm1":"\u0645\u062f\u064a\u0646\u0629 \u0627\u0644\u0643\u0648\u064a\u062a",
    "qs:name_adm2":"\u0645\u062f\u064a\u0646\u0629 \u0627\u0644\u0643\u0648\u064a\u062a",
    "qs:name_local":"\u0645\u062f\u064a\u0646\u0629 \u0627\u0644\u0643\u0648\u064a\u062a",
    "qs:photo_max":74,
    "qs:photo_sum":348,
    "qs:placetype":"Suburb",
    "qs:quad_count":21,
    "qs:woe_adm0":23424870,
    "qs:woe_adm1":20070169,
    "qs:woe_adm2":55943085,
    "qs:woe_lau":0,
    "qs:woe_local":1940631,
    "qs:woe_ver":"7.10.0",
    "wof:lang_x_official":[
        "ara"
    ],
    "wof:lang_x_spoken":[
        "ara"
    ],
    "wof:name":"Salhiya-block 5",
    "wof:placetype":"microhood"
},
  "geometry": {"coordinates":[47.971993,29.367484],"type":"Point"}
}