{
  "type": "Feature",
  "properties": {
    "iso:country":"KW",
    "name:eng_x_preferred":[
        "Fahaheel-block 10"
    ],
    "qs:gn_local":0,
    "qs:local_max":452,
    "qs:local_sum":567,
    "qs:localhoods":2,
    "qs:name":"Fahaheel-block 10",
    "qs:name_adm0":"\u0627\u0644\u0643\u0648\u064a\u062a",
    "qs:name_adm1":"\u0627\u0644\u0623\u062d\u0645\u062f\u0649",
    "qs:name_adm2":"\u0627\u0644\u0623\u062d\u0645\u062f\u0649",
    "qs:name_local":"Al Ifhaihil",
    "qs:photo_max":29,
    "qs:photo_sum":115,
    "qs:placetype":"Suburb",
    "qs:quad_count":11,
    "qs:woe_adm0":23424870,
    "qs:woe_adm1":20070166,
    "qs:woe_adm2":55943081,
    "qs:woe_lau":0,
    "qs:woe_local":1940542,
    "qs:woe_ver":"7.10.0",
    "wof:lang":[
        "eng"
    ],
    "wof:name":"Fahaheel-block 10",
    "wof:placetype":"neighbourhood"
},
  "geometry": {"coordinates":[48.138361,29.091401],"type":"Point"}
}