{
  "type": "Feature",
  "properties": {
    "iso:country":"KW",
    "name:ara_x_preferred":[
        "\u0627\u0644\u0631\u0645\u064a\u062b\u064a\u0629"
    ],
    "name:eng_x_preferred":[
        "Rumaithiya"
    ],
    "name:fas_x_preferred":[
        "\u0627\u0644\u0631\u0645\u06cc\u062b\u06cc\u0647"
    ],
    "name:mzn_x_preferred":[
        "\u0627\u0644\u0631\u0645\u06cc\u062b\u06cc\u0647"
    ],
    "name:swe_x_preferred":[
        "Ar Rumayth\u012byah"
    ],
    "name:urd_x_preferred":[
        "\u0631\u0645\u06cc\u062b\u06cc\u06c1"
    ],
    "qs:gn_pop":0,
    "qs:name":"Rumaithiya",
    "qs:name_adm0":"\u0627\u0644\u0643\u0648\u064a\u062a",
    "qs:name_adm1":"\u062d\u0648\u0644\u0649",
    "qs:photos":13,
    "qs:photos_1k":3,
    "qs:photos_9k":4,
    "qs:photos_9r":6,
    "qs:photos_all":853,
    "qs:photos_sr":1,
    "qs:placetype":"Town",
    "qs:pop_sr":"0",
    "qs:woe_adm0":23424870,
    "wd:wordcount":214,
    "wof:name":"Rumaithiya",
    "wof:placetype":"locality"
},
  "geometry": {"coordinates":[48.06702,29.313379],"type":"Point"}
}