{
  "type": "Feature",
  "properties": {
    "iso:country":"KW",
    "qs:gn_pop":0,
    "qs:name":"Al Ifhaihil",
    "qs:name_adm0":"\u0627\u0644\u0643\u0648\u064a\u062a",
    "qs:name_adm1":"\u0627\u0644\u0623\u062d\u0645\u062f\u0649",
    "qs:photos":63,
    "qs:photos_1k":13,
    "qs:photos_9k":4,
    "qs:photos_9r":6,
    "qs:photos_all":878,
    "qs:photos_sr":2,
    "qs:placetype":"Town",
    "qs:pop_sr":"0",
    "qs:woe_adm0":23424870,
    "wof:name":"Al Ifhaihil",
    "wof:placetype":"locality"
},
  "geometry": {"coordinates":[48.137283,29.08378],"type":"Point"}
}