{
  "type": "Feature",
  "properties": {
    "iso:country":"KW",
    "name:ara_x_colloquial":[
        "As Salihiyah"
    ],
    "name:ara_x_preferred":[
        "As S\u0101lih\u012byah"
    ],
    "name:ara_x_variant":[
        "\u0627\u064e\u0644\u0635\u064e\u0651\u0627\u0644\u0650\u062d\u0650\u064a\u064e\u0651\u0629"
    ],
    "name:unk_x_variant":[
        "A\u015f \u015e\u0101li\u1e29\u012byah",
        "As S\u0101lih\u012byah"
    ],
    "qs:gn_adm0_cc":"KW",
    "qs:gn_fcode":"PPLX",
    "qs:gn_local":285787,
    "qs:gn_nam_loc":"\u0645\u062f\u064a\u0646\u0629 \u0627\u0644\u0643\u0648\u064a\u062a, \u0645\u062f\u064a\u0646\u0629 \u0627\u0644\u0643\u0648\u064a\u062a, \u0645\u062f\u064a\u0646\u0629 \u0627\u0644\u0643\u0648\u064a\u062a, KW",
    "qs:gn_namadm1":"02",
    "qs:gn_name":"A\u015f \u015e\u0101li\u1e29\u012byah",
    "qs:local_max":1268,
    "qs:local_sum":5995,
    "qs:localhoods":31,
    "qs:name":"As S\u0101lih\u012byah",
    "qs:name_adm0":"\u0627\u0644\u0643\u0648\u064a\u062a",
    "qs:name_adm1":"\u0645\u062f\u064a\u0646\u0629 \u0627\u0644\u0643\u0648\u064a\u062a",
    "qs:name_adm2":"\u0645\u062f\u064a\u0646\u0629 \u0627\u0644\u0643\u0648\u064a\u062a",
    "qs:name_local":"\u0645\u062f\u064a\u0646\u0629 \u0627\u0644\u0643\u0648\u064a\u062a",
    "qs:photo_max":56,
    "qs:photo_sum":134,
    "qs:placetype":"Suburb",
    "qs:quad_count":8,
    "qs:woe_adm0":23424870,
    "qs:woe_adm1":20070169,
    "qs:woe_adm2":55943085,
    "qs:woe_lau":0,
    "qs:woe_local":1940631,
    "qs:woe_ver":"7.10.0",
    "wof:lang":[
        "ara"
    ],
    "wof:name":"As S\u0101lih\u012byah",
    "wof:placetype":"neighbourhood"
},
  "geometry": {"coordinates":[47.961543,29.362315],"type":"Point"}
}