{
  "type": "Feature",
  "properties": {
    "iso:country":"KW",
    "qs:gn_pop":0,
    "qs:name":"Salmiya-block 5",
    "qs:name_adm0":"\u0627\u0644\u0643\u0648\u064a\u062a",
    "qs:name_adm1":"\u062d\u0648\u0644\u0649",
    "qs:photos":19,
    "qs:photos_1k":4,
    "qs:photos_9k":1,
    "qs:photos_9r":1,
    "qs:photos_all":19,
    "qs:photos_sr":1,
    "qs:placetype":"Suburb",
    "qs:pop_sr":"0",
    "qs:woe_adm0":23424870,
    "wof:lang_x_official":[
        "ara"
    ],
    "wof:lang_x_spoken":[
        "ara"
    ],
    "wof:name":"Salmiya-block 5",
    "wof:placetype":"neighbourhood"
},
  "geometry": {"coordinates":[48.085012,29.33538],"type":"Point"}
}