{
  "type": "Feature",
  "properties": {
    "gn:admin1_code":"2.0",
    "gn:asciiname":"Ad Dasht",
    "gn:country_code":"KW",
    "gn:dem":2,
    "gn:feature_class":"P",
    "gn:feature_code":"PPLL",
    "gn:name":"Ad Dasht",
    "gn:population":0,
    "gn:timezone":"Asia/Kuwait",
    "iso:country":"KW",
    "name:ara_x_preferred":[
        "\u0627\u064e\u0644\u062f\u064e\u0651\u0634\u0652\u062a"
    ],
    "wof:name":"Ad Dasht",
    "wof:placetype":"locality"
},
  "geometry": {"coordinates":[48.31389,29.4625],"type":"Point"}
}