{
  "type": "Feature",
  "properties": {
    "iso:country":"KW",
    "name:ara_x_preferred":[
        "\u0627\u0644\u062f\u0639\u064a\u0629"
    ],
    "qs:gn_pop":0,
    "qs:name":"Da'iya",
    "qs:name_adm0":"\u0627\u0644\u0643\u0648\u064a\u062a",
    "qs:name_adm1":"\u0645\u062f\u064a\u0646\u0629 \u0627\u0644\u0643\u0648\u064a\u062a",
    "qs:photos":4,
    "qs:photos_1k":1,
    "qs:photos_9k":1,
    "qs:photos_9r":1,
    "qs:photos_all":4,
    "qs:photos_sr":1,
    "qs:placetype":"Suburb",
    "qs:pop_sr":"0",
    "qs:woe_adm0":23424870,
    "wd:wordcount":65,
    "wof:name":"Da'iya",
    "wof:placetype":"neighbourhood"
},
  "geometry": {"coordinates":[48.008639,29.3611485],"type":"Point"}
}