{
  "type": "Feature",
  "properties": {
    "gn:admin1_code":"0.0",
    "gn:asciiname":"Ad Dawhah",
    "gn:country_code":"KW",
    "gn:dem":13,
    "gn:feature_class":"P",
    "gn:feature_code":"PPL",
    "gn:name":"Ad Daw\u1e29ah",
    "gn:population":0,
    "gn:timezone":"Asia/Kuwait",
    "iso:country":"KW",
    "name:ara_x_preferred":[
        "\u0627\u064e\u0644\u062f\u064e\u0651\u0648\u0652\u062d\u064e\u0629"
    ],
    "name:und_x_variant":[
        "Ad Daw\u1e29ah"
    ],
    "wof:lang_x_official":[
        "ara"
    ],
    "wof:lang_x_spoken":[
        "ara"
    ],
    "wof:name":"Ad Dawhah",
    "wof:placetype":"locality"
},
  "geometry": {"coordinates":[47.81194,29.31444],"type":"Point"}
}