{
  "type": "Feature",
  "properties": {
    "gn:admin1_code":"0.0",
    "gn:asciiname":"Al Ad`ami",
    "gn:country_code":"KW",
    "gn:dem":1,
    "gn:feature_class":"P",
    "gn:feature_code":"PPL",
    "gn:name":"Al Ad\u2018am\u012b",
    "gn:population":0,
    "gn:timezone":"Asia/Kuwait",
    "iso:country":"KW",
    "name:ara_x_preferred":[
        "\u0627\u064e\u0644\u0623\u064e\u062f\u0652\u0639\u064e\u0645\u0650\u064a"
    ],
    "name:und_x_variant":[
        "Al Ad\u2018am\u012b"
    ],
    "wof:name":"Al Ad`ami",
    "wof:placetype":"locality"
},
  "geometry": {"coordinates":[48.26667,28.81667],"type":"Point"}
}