{
  "type": "Feature",
  "properties": {
    "iso:country":"KW",
    "name:ara_x_preferred":[
        "\u0642\u0627\u062f\u0633\u064a\u0629"
    ],
    "name:ara_x_variant":[
        "\u0627\u064e\u0644\u0652\u0642\u064e\u0627\u062f\u0650\u0633\u0650\u064a\u064e\u0651\u0629"
    ],
    "name:cat_x_preferred":[
        "Qadisiyya"
    ],
    "name:deu_x_preferred":[
        "Al-Qadisiyya"
    ],
    "name:fas_x_preferred":[
        "\u0642\u0627\u062f\u0633\u06cc\u0647"
    ],
    "name:fra_x_preferred":[
        "Al-Qadisiya"
    ],
    "name:jpn_x_preferred":[
        "\u30a2\u30eb\u30fb\u30ab\u30fc\u30c7\u30a3\u30b7\u30fc\u30e4"
    ],
    "name:kor_x_preferred":[
        "\uc54c\uce74\ub514\uc2dc\uc57c"
    ],
    "name:rus_x_preferred":[
        "\u041a\u0430\u0434\u0438\u0441\u0438\u044f"
    ],
    "name:swe_x_preferred":[
        "Al-Qadisiyyah"
    ],
    "qs:gn_country":"KW",
    "qs:gn_fcode":"PPLX",
    "qs:gn_pop":0,
    "qs:name":"Al Q\u0101dis\u012byah",
    "qs:name_adm0":"\u0627\u0644\u0643\u0648\u064a\u062a",
    "qs:name_adm1":"\u0645\u062f\u064a\u0646\u0629 \u0627\u0644\u0643\u0648\u064a\u062a",
    "qs:photos":1,
    "qs:photos_1k":1,
    "qs:photos_9k":1,
    "qs:photos_9r":1,
    "qs:photos_all":1,
    "qs:photos_sr":1,
    "qs:placetype":"Suburb",
    "qs:pop_sr":"0",
    "qs:woe_adm0":23424870,
    "wof:lang_x_official":[
        "ara"
    ],
    "wof:lang_x_spoken":[
        "ara"
    ],
    "wof:name":"Al Q\u0101dis\u012byah",
    "wof:placetype":"neighbourhood"
},
  "geometry": {"coordinates":[47.985,29.3475],"type":"Point"}
}